{
    "shellTagline":  "Web storefront",
    "footerEyebrow":  "Darwin",
    "footerTitle":  "Fresh shopping, member rewards, and helpful service.",
    "footerDescription":  "Browse the storefront, manage your account, review orders, and find customer support from one clean public web experience.",
    "footerNavigationTitle":  "Footer navigation",
    "primaryNavigationLabel":  "Primary navigation",
    "fallbackPrimaryNavigation":  [
        {
            "label":  "Home",
            "href":  "/"
        },
        {
            "label":  "Shop",
            "href":  "/catalog"
        },
        {
            "label":  "Loyalty",
            "href":  "/loyalty"
        },
        {
            "label":  "Help",
            "href":  "/help"
        },
        {
            "label":  "Contact",
            "href":  "/page/contact"
        }
    ],
    "utilityLinks":  [
        {
            "label":  "Account",
            "href":  "/account"
        },
        {
            "label":  "Cart",
            "href":  "/cart"
        }
    ],
    "footerGroups":  [
        {
            "title":  "Shop",
            "links":  [
                {
                    "label":  "Catalog",
                    "href":  "/catalog"
                },
                {
                    "label":  "Loyalty",
                    "href":  "/loyalty"
                },
                {
                    "label":  "Cart",
                    "href":  "/cart"
                }
            ]
        },
        {
            "title":  "Account",
            "links":  [
                {
                    "label":  "Sign in",
                    "href":  "/account/sign-in"
                },
                {
                    "label":  "Register",
                    "href":  "/account/register"
                },
                {
                    "label":  "My account",
                    "href":  "/account"
                },
                {
                    "label":  "Orders",
                    "href":  "/orders"
                },
                {
                    "label":  "Invoices",
                    "href":  "/invoices"
                }
            ]
        },
        {
            "title":  "Support",
            "links":  [
                {
                    "label":  "Help",
                    "href":  "/help"
                },
                {
                    "label":  "Contact",
                    "href":  "/page/contact"
                },
                {
                    "label":  "Shipping",
                    "href":  "/page/shipping"
                },
                {
                    "label":  "Returns / Cancellation",
                    "href":  "/page/returns"
                }
            ]
        },
        {
            "title":  "Legal",
            "links":  [
                {
                    "label":  "Legal notice",
                    "href":  "/page/legal-notice"
                },
                {
                    "label":  "Privacy",
                    "href":  "/page/privacy-policy"
                },
                {
                    "label":  "Terms",
                    "href":  "/page/terms-and-conditions"
                },
                {
                    "label":  "Cancellation policy",
                    "href":  "/page/cancellation-policy"
                }
            ]
        }
    ]
}
